README.md
setup.py
component_segmentation.egg-info/PKG-INFO
component_segmentation.egg-info/SOURCES.txt
component_segmentation.egg-info/dependency_links.txt
component_segmentation.egg-info/requires.txt
component_segmentation.egg-info/top_level.txt
matrixcomponent/FileScrubber.py
matrixcomponent/JSONparser.py
matrixcomponent/PangenomeSchematic.py
matrixcomponent/Span.py
matrixcomponent/__init__.py
matrixcomponent/matrix.py
matrixcomponent/segmentation.py
matrixcomponent/tests.py
matrixcomponent/utils.py